{"EFTA00031332":{"file_path":"VOL00008/IMAGES/0007/EFTA00031332_extracted.txt","summary_opener":"From: \nTo: Laura Mennin er <Imennin e mflaw.com>, \" \" \n(USANYS)\" \nCc: Jeff Pagliuca ipagliuca@hmflaw.com>, \"Christian R Everdell - Cohen & Gresser LLP \n(ceverdell\u00aecohengressercom)\" <ceverdell\u00aecohengre...","word_count":7789,"entities":[{"entity_name":"Laura Menninger","mention_count":17},{"entity_name":"Jeffrey Epstein","mention_count":8},{"entity_name":"Ghislaine Maxwell","mention_count":6},{"entity_name":"Christian Everdell","mention_count":1}],"known_relationships":[{"source_name":"Jeffrey Epstein","relationship_type":"associate","target_name":"Ghislaine Maxwell"},{"source_name":"Ghislaine Maxwell","relationship_type":"associate","target_name":"Jeffrey Epstein"},{"source_name":"Christian Everdell","relationship_type":"associate","target_name":"Ghislaine Maxwell"},{"source_name":"Laura Menninger","relationship_type":"associate","target_name":"Ghislaine Maxwell"},{"source_name":"Jeffrey Epstein","relationship_type":"associated_with","target_name":"Ghislaine Maxwell"},{"source_name":"Laura Menninger","relationship_type":"attorney_for","target_name":"Ghislaine Maxwell"}],"top_nouns":[{"term":"evidence"},{"term":"item"},{"term":"fbi"},{"term":"review"},{"term":"image"},{"term":"pearl"},{"term":"new"},{"term":"york"}]}}