{"EFTA00023437":{"file_path":"VOL00008/IMAGES/0004/EFTA00023437_extracted.txt","summary_opener":"We have produced all FAA records. Most of the password-locked files were duplicates of the certified files, so we just produced the certified ones.","word_count":2640,"entities":[{"entity_name":"Jeffrey Epstein","mention_count":7}],"known_relationships":[],"top_nouns":[{"term":"air"},{"term":"llc"},{"term":"number"},{"term":"aircraft"},{"term":"inc"},{"term":"faa"},{"term":"tail"},{"term":"visoski"}]}}