{"EFTA00012111":{"file_path":"VOL00008/IMAGES/0001/EFTA00012111_extracted.txt","summary_opener":"DocuSign Envelope ID: 5F5A5466-1857-4351a244-A6FD438E6749 \nS 0tiparlinced \nof Tranoporlaton \nFederal Aviation \nAdministration \nASSIGNMENT OF SPECIAL \nREGISTRATION NUMBERS \nSpecial Registration Number ...","word_count":170947,"entities":[],"known_relationships":[],"top_nouns":[{"term":"aircraft"},{"term":"form"},{"term":"agreement"},{"term":"security"},{"term":"faa"},{"term":"registration"},{"term":"title"},{"term":"interest"}]}}