{"EFTA00035180":{"file_path":"VOL00008/IMAGES/0009/EFTA00035180_extracted.txt","summary_opener":"BP-S358.060 \nSEP 05 MEDICAL TREATMENT REFUSAL CDFRM \nU.S. DEPARTMENT OF JUSTICE FEDERAL BUREAU OF PRISONS \n7-24-2019 \nDate \nI  JEFFREY EPSTEIN 76318-054  , refuse treatment recommended by the Federal ...","word_count":4461,"entities":[{"entity_name":"Jeffrey Epstein","mention_count":20}],"known_relationships":[],"top_nouns":[{"term":"date"},{"term":"bureau"},{"term":"nym"},{"term":"prisons"},{"term":"treatment"},{"term":"new"},{"term":"current"},{"term":"provider"}]}}