{"EFTA00034232":{"file_path":"VOL00008/IMAGES/0009/EFTA00034232_extracted.txt","summary_opener":"Metropolitan Correctional Center, New York, New York SUBJECT:  DHO Checklist/ EPSTEIN. :  76318-054 The UDC refers this case to the DHO, all of the following is attached: PP44 -To determine if the...","word_count":6143,"entities":[{"entity_name":"Jeffrey Epstein","mention_count":68}],"known_relationships":[],"top_nouns":[{"term":"inmate"},{"term":"date"},{"term":"epstein"},{"term":"incident"},{"term":"time"},{"term":"nym"},{"term":"name"},{"term":"staff"}]},"EFTA00034275":{"file_path":"VOL00008/IMAGES/0009/EFTA00034275_extracted.txt","summary_opener":"\u2751 Assault, Attempted On Inmate \u2751 Assault, Attempted On Staff \u2751 Escape From Non-secure Facility \u2751 Escape From Secure Facility \u2751 Escape, Attempted From Non-secure Facility.","word_count":6660,"entities":[{"entity_name":"Jeffrey Epstein","mention_count":56}],"known_relationships":[],"top_nouns":[{"term":"inmate"},{"term":"incident"},{"term":"staff"},{"term":"date"},{"term":"epstein"},{"term":"time"},{"term":"unit"},{"term":"special"}]}}